.gitignore
LICENSE
setup.py
scripts/turkic
turkic/__init__.py
turkic/api.py
turkic/cli.py
turkic/database.py
turkic/geolocation.py
turkic/models.py
turkic/server.py
turkic.egg-info/PKG-INFO
turkic.egg-info/SOURCES.txt
turkic.egg-info/dependency_links.txt
turkic.egg-info/requires.txt
turkic.egg-info/top_level.txt
turkic/public/bg.png
turkic/public/children.jpg
turkic/public/javascript.js
turkic/public/jquery.cookie.js
turkic/public/jquery.js
turkic/public/stylesheet.css
turkic/public/verify.html
turkic/public/wfp.jpg
turkic/skeleton/cli.py
turkic/skeleton/config.py
turkic/skeleton/models.py
turkic/skeleton/server.py
turkic/skeleton/public/index.html
turkic/skeleton/public/javascript.js
turkic/skeleton/public/stylesheet.css