Metadata-Version: 1.0
Name: turkic
Version: 0.2.3
Summary: A framework for Mechanical Turk HITs
Home-page: UNKNOWN
Author: Carl Vondrick
Author-email: cvondric@ics.uci.edu
License: MIT
Platform: UNKNOWN
Classifier: Development Status :: 1 - Planning
Classifier: Intended Audience :: Developers
